pytable/__init__.py
pytable/pytable.py
pytable/tableError.py
pytable/tableTest.py
pytable_console-1.0.dist-info/LICENSE
pytable_console-1.0.dist-info/METADATA
pytable_console-1.0.dist-info/WHEEL
pytable_console-1.0.dist-info/top_level.txt
pytable_console-1.0.dist-info/RECORD
