Metadata-Version: 2.1
Name: pytable-console
Version: 1.0
Summary: Create and edit python tables.
Home-page: https://github.com/McFinnious/pytable/edit/master/README.md
Author: McFinnious
Author-email: finn.custard@gmail.com
License: MIT License
